Workbook

Sheet Sheet1
D1: DYNAMIC SALES ANALYTICS DASHBOARDS | T1: Prepared By HAREESH
A3: No Of Sales Persons | E3: Max Sales Amount | J3: High Product Sold | P3: Min Sales Amount | T3: Sum Of Sales Amount
A4: =COUNTA(Class!C21:C110) -> 90 | E4: =MAX(Class!F21:F110) -> 5000 | J4: Product Z | P4: =MIN(Class!F21:F110) -> 2000 | T4: =SUM(Class!F21:F110) -> 302200

Sheet Class
A1: Dashboard | H1: Trainer: Narendra
A20: Date | B20: Region | C20: Salesperson | D20: Product | E20: Quantity Sold | F20: Sales Amount | G20: Discount (%) | H20: Profit Margin (%) | I20: Total Sales Amount | L20: =Class!A148 -> Additional Columns for Calculation
A21: 45292 | B21: East | C21: Arun Kumar | D21: Product X | E21: 150 | F21: 3000 | G21: 10 | H21: 20 | I21: =E21*F21 -> 450000
A22: 45293 | B22: West | C22: Priya Sharma | D22: Product Y | E22: 200 | F22: 4000 | G22: 15 | H22: 25 | I22: =E22*F22 -> 800000 | K22: Q 1 | M22: Q 2 | O22: Q 3 | Q22: Q 4
A23: 45294 | B23: North | C23: Rajesh Patel | D23: Product X | E23: 120 | F23: 2400 | G23: 5 | H23: 18 | I23: =E23*F23 -> 288000 | K23: {=Class!E21:E110*Class!F21:F110} -> 450000 | M23: {=Class!F21:F110*(Class!H21:H110/100)} -> 600 | O23: {=Class!F21:F110-(Class!F21:F110*(Class!G21:G110/100))} -> 2700 | Q23: {=Class!I21:I110*(Class!H21:H110/100)} -> 90000
A24: 45295 | B24: South | C24: Meera Reddy | D24: Product Z | E24: 250 | F24: 5000 | G24: 20 | H24: 30 | I24: =E24*F24 -> 1250000 | K24: 800000 | M24: 1000 | O24: 3400 | Q24: 200000
A25: 45296 | B25: East | C25: Arun Kumar | D25: Product Y | E25: 100 | F25: 2000 | G25: 10 | H25: 22 | I25: =E25*F25 -> 200000 | K25: 288000 | M25: 432 | O25: 2280 | Q25: 51840
A26: 45297 | B26: West | C26: Priya Sharma | D26: Product X | E26: 180 | F26: 3600 | G26: 12 | H26: 19 | I26: =E26*F26 -> 648000 | K26: 1250000 | M26: 1500 | O26: 4000 | Q26: 375000
A27: 45298 | B27: North | C27: Rajesh Patel | D27: Product Y | E27: 150 | F27: 3000 | G27: 8 | H27: 21 | I27: =E27*F27 -> 450000 | K27: 200000 | M27: 440 | O27: 1800 | Q27: 44000
A28: 45299 | B28: South | C28: Meera Reddy | D28: Product X | E28: 200 | F28: 4000 | G28: 15 | H28: 27 | I28: =E28*F28 -> 800000 | K28: 648000 | M28: 684 | O28: 3168 | Q28: 123120
A29: 45300 | B29: East | C29: Arun Kumar | D29: Product Z | E29: 170 | F29: 3400 | G29: 18 | H29: 23 | I29: =E29*F29 -> 578000 | K29: 450000 | M29: 630 | O29: 2760 | Q29: 94500
A30: 45301 | B30: West | C30: Priya Sharma | D30: Product Z | E30: 130 | F30: 2600 | G30: 10 | H30: 20 | I30: =E30*F30 -> 338000 | K30: 800000 | M30: 1080 | O30: 3400 | Q30: 216000
A31: 45302 | B31: North | C31: Rajesh Patel | D31: Product X | E31: 160 | F31: 3200 | G31: 5 | H31: 22 | I31: =E31*F31 -> 512000 | K31: 578000 | M31: 782 | O31: 2788 | Q31: 132940
A32: 45303 | B32: South | C32: Meera Reddy | D32: Product Y | E32: 180 | F32: 3600 | G32: 12 | H32: 25 | I32: =E32*F32 -> 648000 | K32: 338000 | M32: 520 | O32: 2340 | Q32: 67600
A33: 45304 | B33: East | C33: Arun Kumar | D33: Product Y | E33: 140 | F33: 2800 | G33: 11 | H33: 24 | I33: =E33*F33 -> 392000 | K33: 512000 | M33: 704 | O33: 3040 | Q33: 112640
A34: 45305 | B34: West | C34: Priya Sharma | D34: Product X | E34: 150 | F34: 3000 | G34: 8 | H34: 20 | I34: =E34*F34 -> 450000 | K34: 648000 | M34: 900 | O34: 3168 | Q34: 162000
A35: 45306 | B35: North | C35: Rajesh Patel | D35: Product Z | E35: 190 | F35: 3800 | G35: 7 | H35: 19 | I35: =E35*F35 -> 722000 | K35: 392000 | M35: 672 | O35: 2492 | Q35: 94080
... A110: 45382 | B110: South | C110: Meera Reddy | D110: Product Y | E110: 180 | F110: 3600 | G110: 17 | H110: 28 | I110: =E110*F110 -> 648000 | K110: 800000 | M110: 840 | O110: 3560 | Q110: 168000
K111: 512000 | M111: 704 | O111: 2944 | Q111: 112640
K112: 648000 | M112: 1008 | O112: 2988 | Q112: 181440
A114: Dashboard Questions & Visualization Suggestions
A116: 1. Date
A117: What to Do: Analyze sales trends over time.
A118: Visualizations: Line chart - Quantity Sold, Area chart - showing Sales Amount over the dates.
A120: 2. Region
A121: What to Do: Compare sales performance across different regions.
A122: Visualizations: Bar chart - Total Sales Amount, pie chart - Quantity Sold, by Region.
A124: 3. Salesperson
A125: What to Do: Evaluate performance of each salesperson.
A126: Visualizations: Bar chart - Profit Margin by Salesperson.
A128: 4. Product
A129: What to Do: Understand sales distribution by product type.
... A174: 4. Build the Dashboard: Arrange your visualizations and tables on a new worksheet. Use slicers and pivot tables to make your dashboard interactive.
